django_es_drf/__init__.py
django_es_drf/document.py
django_es_drf/document_generator.py
django_es_drf/document_registry.py
django_es_drf/drf/__init__.py
django_es_drf/drf/aggs.py
django_es_drf/drf/backends/__init__.py
django_es_drf/drf/backends/filters.py
django_es_drf/drf/backends/query_interpreters.py
django_es_drf/drf/backends/source.py
django_es_drf/drf/pagination.py
django_es_drf/drf/renderers.py
django_es_drf/drf/serializers.py
django_es_drf/drf/viewsets.py
django_es_drf/indexer.py
django_es_drf/json.py
django_es_drf/nested.py
django_es_drf/serializer_generator.py
django_es_drf/settings.py
django_es_drf/signals.py
django_es_drf-1.0.0a18.dist-info/WHEEL
django_es_drf-1.0.0a18.dist-info/METADATA
django_es_drf-1.0.0a18.dist-info/RECORD
