Metadata-Version: 2.1
Name: django-es-drf
Version: 1.0.0a18
Summary: Simple django - elasticsearch - drf integration
Author: Mirek Simek
Author-email: miroslav.simek@vscht.cz
Requires-Python: >=3.9,<4.0
Classifier: Programming Language :: Python :: 3
Classifier: Programming Language :: Python :: 3.9
Classifier: Programming Language :: Python :: 3.10
Requires-Dist: django (>=4,<5)
Requires-Dist: djangorestframework (>=3.13.1,<4.0.0)
Requires-Dist: elasticsearch-dsl (>=7,<8)
Requires-Dist: lazy-object-proxy (>=1.7.1,<2.0.0)
Requires-Dist: luqum (>=0.11.0,<0.12.0)
